{
  "source": "https://undocs.org/en/S/RES/2629(2022)",
  "pdf": {
    "version": "1.10.100",
    "info": {
      "PDFFormatVersion": "1.7",
      "IsAcroFormPresent": false,
      "IsXFAPresent": false,
      "Author": "Carla Mavrodin",
      "Creator": "Microsoft速 Word for Microsoft 365",
      "Producer": "Microsoft速 Word for Microsoft 365",
      "CreationDate": "D:20220503161751-04'00'",
      "ModDate": "D:20220503161751-04'00'"
    },
    "metadata": {
      "_metadata": {
        "pdf:producer": "Microsoft速 Word for Microsoft 365",
        "dc:creator": "Carla Mavrodin",
        "xmp:creatortool": "Microsoft速 Word for Microsoft 365",
        "xmp:createdate": "2022-05-03T16:17:51-04:00",
        "xmp:modifydate": "2022-05-03T16:17:51-04:00",
        "xmpmm:documentid": "uuid:3DE31E22-3A1C-4C42-8D87-8F999F0B1A1E",
        "xmpmm:instanceid": "uuid:3DE31E22-3A1C-4C42-8D87-8F999F0B1A1E"
      }
    },
    "totalPages": 2
  },
  "summary": " The Security Council adopted Resolution 2629 (2022) to extend the mandate of the United Nations Support Mission in Libya (UNSMIL) until July 31, 2022. The resolution reaffirms the Council's commitment to a Libyan-led and Libyan-owned political process, and calls for the implementation of the timeline elaborated in the Libyan Political Dialogue Forum (LPDF) roadmap. It also demands full compliance with the arms embargo imposed under Resolution 1970 (2011), and requests the Secretary-General to report to the Security Council on the implementation of the resolution every 30 days.",
  "id": "S/RES/2629(2022)",
  "author": "Carla Mavrodin",
  "title": "S/RES/2629(2022)"
}