{
  "source": "https://www.undocs.org/A/RES/77/249",
  "pdf": {
    "version": "1.10.100",
    "info": {
      "PDFFormatVersion": "1.7",
      "IsAcroFormPresent": false,
      "IsXFAPresent": false,
      "Author": "Andrea Chambers",
      "Creator": "Microsoft速 Word for Microsoft 365",
      "Producer": "Microsoft速 Word for Microsoft 365",
      "CreationDate": "D:20230112155842-05'00'",
      "ModDate": "D:20230112155842-05'00'"
    },
    "metadata": {
      "_metadata": {
        "pdf:producer": "Microsoft速 Word for Microsoft 365",
        "dc:creator": "Andrea Chambers",
        "xmp:creatortool": "Microsoft速 Word for Microsoft 365",
        "xmp:createdate": "2023-01-12T15:58:42-05:00",
        "xmp:modifydate": "2023-01-12T15:58:42-05:00",
        "xmpmm:documentid": "uuid:CC98E67A-CFD5-44D7-9B75-585883B2E625",
        "xmpmm:instanceid": "uuid:CC98E67A-CFD5-44D7-9B75-585883B2E625"
      }
    },
    "totalPages": 2
  },
  "summary": " The United Nations General Assembly adopted Resolution 77/249 on 30 December 2022, which expresses appreciation to the International Law Commission for its contribution to the codification and progressive development of international law, takes note of the draft articles on prevention and punishment of crimes against humanity, and decides that the Sixth Committee shall resume its session for five days in 2023 and six days in 2024 to exchange views on the draft articles and consider the recommendation of the Commission for the elaboration of a convention. It also invites States to submit written comments and observations on the draft articles and requests the Secretary-General to prepare and circulate a compilation of those comments and observations.",
  "id": "A/RES/77/249",
  "author": "Andrea Chambers",
  "title": "A/RES/77/249"
}